{
  "date": "2026-06-04",
  "conference": {
    "slug": "asco-2026",
    "name": "ASCO Annual Meeting 2026"
  },
  "generated_at": 1784442773493,
  "digest": {
    "top_line": "AREST: adjuvant RT cuts 3-yr loco-regional failure in resected intermediate-risk oral SCC — LRFS 89.2% vs 80.9%, HR 0.52 (0.30-0.91), p=0.02; no OS/DFS gain.",
    "tldr": "Head/neck carried the day: AREST is the first randomized evidence that adjuvant RT (60Gy/30fx) improves loco-regional control in resected pN0 intermediate-risk oral SCC, though the LC gain doesn't reach OS/DFS. Prostate news is a practice gap: an MROQC registry finds just 67% of definitive-RT high-risk pts get guideline-concordant ADT, ARPI intensification only 23%.",
    "sites": [
      {
        "disease_site": "prostate",
        "intro": "A practice-pattern registry, not a trial: how often high-risk pts on definitive RT actually get guideline-concordant ADT and STAMPEDE-era ARPI intensification.",
        "studies": [
          {
            "name": "MROQC ADT Practice Patterns",
            "tldr": "Guideline-concordant ADT (≥18mo) recommended in 67.0% of high-risk pts on definitive RT; ARPI intensification just 23.2% of STAMPEDE-eligible.",
            "details": [
              "📊 Primary outcome: 67.0% of 553 pts recommended guideline-concordant ADT (≥18mo)",
              "📊 91.3% recommended any ADT; a third fell short of the ≥18mo guideline duration",
              "💊 ARPI intensification in STAMPEDE-eligible pts: 0% pre-publication → 23.2% after STAMPEDE M0",
              "🔍 Prospective MROQC registry, 26 RT centers, Jun 2020–Nov 2024; intact high-risk M0/N0-1 prostate",
              {
                "text": "🔍 Baseline high-risk features",
                "subdetails": [
                  "GG4-5: 75.0%",
                  "PSA ≥20 ng/mL: 40.0%",
                  "cN1: 19.9%",
                  "cT3/4: 13.3%",
                  "Met STAMPEDE M0 intensification criteria: 27.9%"
                ]
              },
              {
                "text": "📊 Predictors of guideline-concordant ADT (multivariable ORs)",
                "table": {
                  "columns": [
                    "Factor",
                    "OR (GC-ADT)",
                    "95% CI"
                  ],
                  "rows": [
                    [
                      "cN1",
                      "2.94",
                      "1.44-5.99"
                    ],
                    [
                      "GG4",
                      "6.23",
                      "2.85-13.62"
                    ],
                    [
                      "GG5",
                      "9.45",
                      "4.46-20.06"
                    ],
                    [
                      "PSA ≥40",
                      "3.64",
                      "1.22-10.87"
                    ]
                  ]
                }
              },
              "⚠️ Facility-level variability persisted on MVA (P<.0001); treating site shifts the ADT recommendation",
              "⚠️ Captures intended ADT duration + recommendations, not delivered treatment or adherence",
              "🔗 vs 2022 AUA/ASTRO guideline (18-36mo ADT) + STAMPEDE M0: documents the adoption gap"
            ],
            "figures": [],
            "nct": null,
            "tweet_ids": [
              1000000019
            ],
            "slug": "prostate-adt-practice-patterns",
            "verdict": {
              "soc_implication": "confirmatory",
              "rationale": "Descriptive practice-pattern audit (no efficacy endpoint); reinforces AUA/ASTRO ADT guideline and STAMPEDE M0 as benchmark, documenting under-adoption rather than testing a new effect.",
              "audience": "High-risk M0/N0-1 prostate on definitive RT, GG4-5 predominant"
            },
            "significance": "The RT prescriber's read is the adoption gap, not a treatment effect: even in a quality consortium, only 67.0% of high-risk pts on definitive RT are recommended ≥18mo ADT, and just 23.2% of STAMPEDE-eligible get ARPI intensification. Facility-level variability persists on multivariable analysis (P<.0001), so where a man is treated, not only his risk, sets his ADT. Prompts an audit of your own duration and intensification practice.",
            "monday_clinic": "In high-risk men (GG4-5, cN1, PSA ≥40, or ≥2 STAMPEDE factors) starting definitive RT, this supports benchmarking ADT to ≥18mo and weighing ARPI intensification when STAMPEDE-eligible; it does not extend to low/intermediate-risk disease or ADT-omission decisions.",
            "primary_endpoint": null,
            "analysis_sections": [
              {
                "label": "Design",
                "body": "Prospective practice-pattern study within the **Michigan Radiation Oncology Quality Consortium (MROQC)**, a statewide RT registry. **553 pts across 26 centers**, Jun 2020–Nov 2024. Facility modeled as a random intercept (mixed-effects)."
              },
              {
                "label": "Population & inclusion",
                "body": "Intact, **high-risk M0/N0-1** prostate cancer on definitive RT. **GG4-5 75.0%**, PSA ≥20 40.0%, cN1 19.9%, cT3/4 13.3%. **27.9%** met STAMPEDE M0 intensification criteria."
              },
              {
                "label": "Endpoints",
                "body": "**Primary: intended guideline-concordant ADT (≥18mo).** Also assessed: ARPI adoption before vs after STAMPEDE M0 publication, facility-level variability, and multivariable predictors of concordance."
              },
              {
                "label": "Results",
                "body": "**91.3%** recommended any ADT, **67.0%** guideline-concordant. ARPI intensification among STAMPEDE-eligible rose **0% → 23.2%** post-publication. Facility variability persisted on MVA (**P<.0001**)."
              },
              {
                "label": "vs leading data",
                "body": "Benchmarks real practice against the 2022 **AUA/ASTRO** guideline (18-36mo ADT) and **STAMPEDE M0** (ARPI for high-burden high-risk). Documents a persistent **adoption gap**, not a treatment effect."
              },
              {
                "label": "Applies to",
                "body": "Represents high-risk M0/N0-1 prostate treated with definitive RT within a quality consortium. Does not represent low/intermediate-risk disease, national non-consortium practice, or delivered (vs intended) treatment."
              },
              {
                "label": "Limitations",
                "body": "Captures **intended** ADT duration and recommendations, not delivered therapy or adherence. Single-state consortium limits generalizability, and there is no efficacy or outcome endpoint."
              }
            ],
            "relevant_specialties": [
              "radonc",
              "medonc"
            ],
            "open_questions": [
              "Does intended guideline-concordant ADT translate to delivered treatment and adherence?",
              "What interventions reduce facility-level variability in ADT recommendations?",
              "Do Michigan consortium patterns generalize to national practice?"
            ],
            "consort": null,
            "modality": "systemic",
            "intent": "curative",
            "methodology": "real-world-evidence",
            "significance_perspective": "Radiation oncology",
            "related_trials": null,
            "related_trials_provenance": {
              "queries_fired": [],
              "queries_failed": [],
              "candidates_returned": 0,
              "fetched_at": "2026-07-19T06:29:02.651Z",
              "rerank_outcome": "skipped"
            },
            "source_ids": [
              {
                "type": "paper",
                "id": 19
              }
            ]
          }
        ],
        "open_questions": null
      },
      {
        "disease_site": "head-neck",
        "intro": "First randomized test of adjuvant RT in the resected pN0 intermediate-risk oral-cavity setting, where prior evidence was only retrospective.",
        "studies": [
          {
            "name": "AREST",
            "tldr": "3-yr LRFS 89.2% vs 80.9%, HR 0.52 (0.30-0.91) p=0.02 favoring adjuvant RT in resected intermediate-risk pT1-2N0 oral SCC; no OS/DFS gain.",
            "details": [
              "🔍 Phase III open-label RCT (India), N=392 (191 RT vs 201 observation); 1° endpoint 3-yr LRFS, stratified by subsite/PNI-LVE/differentiation",
              "🔍 Eligible after adequate surgery: margins ≥5mm + ipsilateral level I-III neck dissection with ≥16 nodes",
              {
                "text": "🔍 Intermediate-risk features (any one qualified)",
                "subdetails": [
                  "DOI ≥5 to ≤10mm",
                  "Perineural invasion (PNI)",
                  "Lymphovascular emboli (LVE)",
                  "Poor differentiation"
                ]
              },
              "📐 Adjuvant RT: 60Gy/30fx over 6wks to resected tumor bed + at-risk neck nodal region",
              {
                "text": "📊 Cumulative incidence of loco-regional failure (death as competing event)",
                "table": {
                  "columns": [
                    "Analysis",
                    "Adjuvant RT",
                    "Observation",
                    "HR (95% CI), p"
                  ],
                  "rows": [
                    [
                      "ITT",
                      "10.6% (6.1-15.1)",
                      "18.9% (13.3-24.6)",
                      "0.52 (0.30-0.91), p=0.021"
                    ],
                    [
                      "Per-protocol",
                      "8.7% (4.3-13.1)",
                      "18.9% (13.3-24.6)",
                      "0.43 (0.23-0.79), p=0.007"
                    ]
                  ]
                }
              },
              "📊 Oral tongue derived higher adjuvant-RT benefit than buccal mucosa (exploratory subgroup)",
              "⚠️ No OS or DFS benefit at 47.2mo median f/u; loco-regional control gain only",
              "⚠️ Powered for HR 0.6256 assuming 70% 3-yr LRFS in observation; actual observation 80.9% (event rate lower than assumed)",
              "🔗 First randomized evidence in this pN0 intermediate-risk setting; prior data was retrospective per the abstract"
            ],
            "figures": [
              {
                "url": "https://pbs.twimg.com/media/HJVgwera0AAs6s2.jpg",
                "caption": {
                  "columns": [
                    "Arm",
                    "3-yr LRFS",
                    "HR (95% CI)",
                    "p"
                  ],
                  "rows": [
                    [
                      "Adjuvant RT",
                      "89.2% (84.3-93.3)",
                      "0.52 (0.30-0.91)",
                      "0.02"
                    ],
                    [
                      "Observation",
                      "80.9% (74.6-86.1)",
                      "ref",
                      "—"
                    ]
                  ]
                }
              }
            ],
            "nct": null,
            "tweet_ids": [
              71,
              1000000018
            ],
            "slug": "arest",
            "verdict": {
              "soc_implication": "confirmatory",
              "rationale": "First randomized backing for the guideline-listed retrospective signal that RT cuts LRR in adverse-feature pN0 OSCC; loco-regional benefit only, no OS/DFS, open-label abstract.",
              "audience": "Adequately resected pT1-2N0 oral SCC with ≥1 intermediate-risk feature"
            },
            "significance": "The move is observe-vs-treat in adequately resected pT1-2N0 OSCC with one adverse feature: 60Gy/30fx to tumor bed plus at-risk neck cut 3-yr loco-regional failure (HR 0.52), strongest in oral tongue over buccal mucosa (exploratory). The gain is loco-regional only, so weigh it against RT morbidity when baseline LRR risk is low.",
            "monday_clinic": "In an adequately resected pT1-2N0 oral tongue SCC with a single intermediate-risk feature, this supports adjuvant RT for loco-regional control but not survival, and it does not extend to buccal mucosa (weaker signal) or node-positive disease.",
            "primary_endpoint": {
              "name": "Loco-regional recurrence-free survival",
              "klass": "local-control",
              "stat_value": "HR 0.52",
              "stat_detail": "3-yr LRFS 89.2% vs 80.9%, 95% CI 0.30-0.91, p=0.02 (ITT)"
            },
            "analysis_sections": [
              {
                "label": "Design",
                "body": "Phase 3, open-label, multicenter RCT (India); 1:1 to adjuvant RT vs observation, **N=392** (191 RT, 201 observation), stratified by subsite, PNI/LVE, differentiation. Median follow-up **47.2 months**."
              },
              {
                "label": "Population & inclusion",
                "body": "**pT1-2 pN0** OSCC with ≥1 intermediate-risk feature (**DOI 5-10mm, PNI, LVE, or poor differentiation**), after adequate surgery: margins **≥5mm** and ipsilateral level I-III neck dissection with **≥16 nodes**."
              },
              {
                "label": "Radiotherapy",
                "body": "**60Gy in 30 fractions** over 6 weeks to the resected tumor bed and at-risk neck nodal region."
              },
              {
                "label": "Endpoints",
                "body": "**Primary: 3-yr loco-regional recurrence-free survival (LRFS)**, KM with log-rank. Secondary: DFS, OS, and cumulative incidence of loco-regional failure (competing-risk)."
              },
              {
                "label": "Results",
                "body": "Per-protocol LRFS **91.1% vs 80.9%, HR 0.43 (0.23-0.80), p=0.01**. DFS and OS **not significantly different** between arms."
              },
              {
                "label": "vs leading data",
                "body": "Prior evidence for adjuvant RT in this pN0 intermediate-risk setting was **retrospective** (per the abstract); AREST is the first randomized confirmation."
              },
              {
                "label": "Applies to",
                "body": "Represents adequately resected pT1-2 pN0 oral SCC (margins ≥5mm, ≥16-node neck dissection) with one intermediate-risk feature. Does not represent node-positive disease, positive/close margins, or inadequately staged necks."
              },
              {
                "label": "Limitations",
                "body": "Open-label, abstract-only; benefit is **loco-regional control only, no OS/DFS** at 47.2-mo median. Observation LRFS (80.9%) exceeded the 70% powering assumption, so the absolute LRFS gain is modest."
              }
            ],
            "relevant_specialties": [
              "radonc",
              "surgonc"
            ],
            "open_questions": [
              "Does loco-regional control benefit translate to survival with longer follow-up?",
              "Optimal adjuvant approach for buccal mucosa vs oral tongue subsites?",
              "Which single intermediate-risk feature drives the RT benefit?"
            ],
            "consort": {
              "enrolled": null,
              "excluded": null,
              "randomized": 392,
              "arms": [
                {
                  "label": "Adjuvant RT",
                  "allocated": 191,
                  "analyzed": null
                },
                {
                  "label": "Observation",
                  "allocated": 201,
                  "analyzed": null
                }
              ]
            },
            "modality": "radiation",
            "intent": "curative",
            "methodology": "phase-3-rct",
            "significance_perspective": "Radiation oncology",
            "related_trials": [
              {
                "nct": "NCT07457099",
                "brief_title": "Impact of Postoperative Radiotherapy Versus PD-1 Inhibitor Maintenance on Survival in Resectable Locally Advanced Oral and Oropharyngeal Squamous Cell Carcinoma",
                "overall_status": "NOT_YET_RECRUITING",
                "phase": null,
                "enrollment_count": 85,
                "primary_completion_date": "2026-08",
                "brief_summary": "Neoadjuvant immunochemotherapy (NAIC) has demonstrated promising pathological and survival outcomes in patients with resectable locally advanced oral and oropharyngeal squamous cell carcinoma (LA-OSCC/OPSCC). However, the optimal postoperative management strategy following NAIC and radical surgery remains undefined, particularly regarding the necessity of postoperative radiotherapy and the potential role of PD-1 inhibitor maintenance therapy.\n\nThis single-center, ambispective cohort study aims…",
                "conditions": [
                  "Locally Advanced Oral Squamous Cell Carcinoma",
                  "Locally Advanced Oropharyngeal Squamous Cell Carcinoma"
                ],
                "interventions": [
                  {
                    "name": "Observation",
                    "type": "OTHER"
                  },
                  {
                    "name": "Postoperative Radiotherapy",
                    "type": "RADIATION"
                  },
                  {
                    "name": "PD-1 Inhibitor Maintenance Therapy",
                    "type": "DRUG"
                  }
                ],
                "eligibility_brief": "Inclusion Criteria:\n\n1. Age 18-80 years, any gender.\n2. Expected survival ≥ 6 months.\n3. Adequate major organ function; ECOG performance status 0-1.\n4. Treatment-naïve patients diagnosed with locally advanced oral squamous cell carcinoma (LA-OSCC) or locally advanced oropharyngeal squamous cell…",
                "answers_question": "Does loco-regional control benefit translate to survival with longer follow-up?",
                "relevance_phrase": "postop RT vs PD-1 maintenance, survival endpoint"
              },
              {
                "nct": "NCT06485778",
                "brief_title": "A Study of Radiation Therapy After Surgery in People With Oral Tongue Squamous Cell Carcinoma",
                "overall_status": "RECRUITING",
                "phase": [
                  "PHASE2"
                ],
                "enrollment_count": 24,
                "primary_completion_date": "2027-06",
                "brief_summary": "This study will test whether limiting standard photon intensity modulated radiation therapy (IMRT) to exclude the oral tongue surgical site can decrease the risk of side effects caused by oral radiation. The researchers will also find out if this approach affects the rate of disease coming back after treatment (recurrence), and will measure participants' quality of life by having them complete questionnaires.",
                "conditions": [
                  "Oral Tongue Squamous Cell Carcinoma"
                ],
                "interventions": [
                  {
                    "name": "Photon intensity modulated radiation therapy (IMRT)",
                    "type": "RADIATION"
                  },
                  {
                    "name": "Life questionnaire's",
                    "type": "OTHER"
                  }
                ],
                "eligibility_brief": "Inclusion Criteria:\n\n* Age ≥ 18\n* Surgical resection of all gross disease without evidence of residual loco-regional disease on simulation PET/CT.\n* pT1-2, or pT3 by DOI, pN0-2b Squamous Cell Carcinoma of the Oral Tongue confirmed on final surgical pathology. Patients must have:\n\n  * at least two…",
                "answers_question": "Optimal adjuvant approach for buccal mucosa vs oral tongue subsites?",
                "relevance_phrase": "postop IMRT tailored to oral tongue subsite"
              }
            ],
            "related_trials_provenance": {
              "queries_fired": [
                "oral cavity adjuvant radiotherapy",
                "oral tongue adjuvant radiation"
              ],
              "queries_failed": [],
              "candidates_returned": 27,
              "fetched_at": "2026-07-19T06:31:08.624Z",
              "rerank_outcome": "picked_N"
            },
            "source_ids": [
              {
                "type": "tweet",
                "id": 71
              },
              {
                "type": "paper",
                "id": 18
              }
            ]
          }
        ],
        "open_questions": null
      }
    ],
    "meta": {
      "clusters_total": 2,
      "studies_analyzed": 2,
      "dropped": [],
      "ocr_available": true
    }
  },
  "bookmarks": [
    {
      "id": 71,
      "url": "https://x.com/DrRishabhOnco/status/2059658801587122327",
      "bookmark_date": "2026-06-04",
      "author_handle": "@DrRishabhOnco",
      "author_name": "Dr Rishabh Jain",
      "text": "#ASCO26 \n\n🗣️ The AREST trial tackles one of the biggest gray zones in oral cavity cancer.\n\nAfter adequate surgery in pT1-2N0 OSCC with intermediate-risk features:\n\n✅ Adjuvant RT improved loco-regional control\n❌ No OS benefit observed\n\n3-year LRFS:\n🔹 89.2% vs 80.9%\n🔹 HR 0.52… https://t.co/qsALPFX032 pic.twitter.com/F4XzTMETih",
      "html": "<blockquote class=\"twitter-tweet\"><p lang=\"en\" dir=\"ltr\"><a href=\"https://x.com/hashtag/ASCO26?src=hash&amp;ref_src=twsrc%5Etfw\">#ASCO26</a> <br><br>🗣️ The AREST trial tackles one of the biggest gray zones in oral cavity cancer.<br><br>After adequate surgery in pT1-2N0 OSCC with intermediate-risk features:<br><br>✅ Adjuvant RT improved loco-regional control<br>❌ No OS benefit observed<br><br>3-year LRFS:<br>🔹 89.2% vs 80.9%<br>🔹 HR 0.52… <a href=\"https://t.co/qsALPFX032\">https://t.co/qsALPFX032</a> <a href=\"https://t.co/F4XzTMETih\">pic.twitter.com/F4XzTMETih</a></p>&mdash; Dr Rishabh Jain (@DrRishabhOnco) <a href=\"https://x.com/DrRishabhOnco/status/2059658801587122327?ref_src=twsrc%5Etfw\">May 27, 2026</a></blockquote>\n\n",
      "image_urls": [
        "https://pbs.twimg.com/media/HJVgwera0AAs6s2.jpg"
      ],
      "image_ocr_texts": [
        "#ASCO26\nAbstract 6000\nSHOULD ALL\nINTERMEDIATE-RISK\nEARLY ORAL CAVITY CANCERS\nGET RT?\nASCO\nAMERICAN SOCIETY OF CLINICAL ONCOLOGY\nKNOWLEDGE CONQUERS CANCER\n?\n@DrRishabhOnco\nAREST Trial: Adjuvant radiotherapy vs observation\nafter curative surgery for early-stage (pT1-2NO)\noral squamous cell carcinoma with intermediate-risk features\n3-YEAR LOCO-REGIONAL RECURRENCE-FREE SURVIVAL (LRFS)\nADJUVANT RT\n89.2%\n(95% CI: 84.3% - 93.3%)\nHR\n0.52\n(95% CI: 0.30-0.91)\np = 0.02\nOBSERVATION\n80.9%\n(95% Cl: 74.6% - 86.1%)\nBetter\nloco-regional control\nNo overall survival\nbenefit yet\n(No significant difference in DFS or OS\nat median follow-up of 47.2 months)\n* EXPLORATORY FINDING\nSignal appears\nstronger in\noral tongue tumors\nShared decision-making\nremains key.\nMulticenter\nPhase III RCT\nfrom India\nN = 392\n(191 RT vs 201\nObservation)\nPrimary endpoint\nLRFS\nMedian follow-up\n47.2 months\nJ Clin Oncol 44, 2026 (suppl 16; abstr 6000) | DOI: 10.1200/JCO.2026.44.16_suppl.6000\nCTRI/2017/07/009114"
      ],
      "note": null,
      "fetched_via": "oembed",
      "conference_slug": "asco-2026"
    }
  ],
  "papers": [
    {
      "id": 19,
      "pmid": null,
      "doi": "10.1200/op-25-00489",
      "pmc_id": null,
      "title": "Androgen Deprivation Therapy Practice Patterns in High-Risk Prostate Cancer Treated With Definitive Radiotherapy: Prospective Results From a Statewide Quality Consortium",
      "authors": [
        "Dykstra, Michael P.",
        "Regan, Samuel N.",
        "Yin, Huiying (Maggie)",
        "McLaughlin, Patrick William",
        "Zaki, Mark",
        "Mislmani, Mazen",
        "Miller, Steven R.",
        "Narayana, Vrinda",
        "Kendrick, Danielle",
        "Khadija, Murshed",
        "Dryden, Daniel",
        "Litzenberg, Dale W.",
        "Mietzel, Melissa",
        "Heimburger, David K.",
        "Schipper, Matthew",
        "Jackson, William C.",
        "Dess, Robert T."
      ],
      "journal": "JCO Oncology Practice",
      "pub_date": "2025-09-26",
      "abstract": "PURPOSE The 2022 AUA/ASTRO guidelines recommend 18-36 months of androgen deprivation therapy (ADT) with definitive radiotherapy for localized, high-risk prostate cancer. The STAMPEDE M0 trial supports intensification with androgen receptor pathway inhibitors (ARPIs) for patients with ≥2 cT3/T4, Grade Group [GG] 4-5, prostate-specific antigen (PSA) ≥40 ng/mL, or cN1. Given advances in imaging, risk stratification, and treatment delivery, we characterized contemporary practice patterns using prospective data from the Michigan Radiation Oncology Quality Consortium (MROQC). METHODS Patients enrolled in MROQC with intact, high-risk M0/N0-1 prostate cancer were included. Clinical information, including intended ADT duration and ARPI use, was prospectively collected. The primary outcome was intended guideline-concordant ADT (GC-ADT, ≥18 months). Multivariable analyses (MVA) assessed associations between clinical factors and GC-ADT recommendations. We compared the adoption of ARPI with standard therapies before and after the publication of STAMPEDE M0. Facility-level variability was evaluated using a mixed-effects model, with the treatment site as a random intercept. RESULTS Between June 2020 and November 2024, 553 patients across 26 centers were included: cT3/4 (13.3%), cN1 (19.9%), GG 4-5 (75.0%), and PSA ≥20 ng/mL (40.0%). Overall, 91.3% were recommended ADT, with 67.0% being guideline-concordant. On MVA, GC-ADT was significantly associated with cN1 (odds ratio [OR], 2.94 [95% CI, 1.44 to 5.99]), GG (GG4 OR, 6.23 [95% CI, 2.85 to 13.62]; GG5 OR, 9.45 [95% CI, 4.46 to 20.06]), and PSA ≥40 (OR, 3.64 [95% CI, 1.22–10.87]). Facility-level variability persisted in the MVA ( P &lt; .0001). Among the 27.9% who met meeting STAMPEDE criteria, ARPI recommendations increased from 0% prepublication to 23.2% afterward. CONCLUSION Within a statewide quality consortium, guideline-concordant ADT recommendations occurred in two thirds of patients, with ARPI intensification in under 25% among STAMPEDE-eligible patients. These findings highlight the need for individualized ADT strategies and collaborative efforts to standardize high-quality care.",
      "pdf_path": "data/obsidian/papers/prostate/androgen-deprivation-therapy-practice-patterns-in-high-risk-pros.pdf",
      "source_url": null,
      "note": null,
      "resolved_from_review": false
    },
    {
      "id": 18,
      "pmid": null,
      "doi": "10.1200/jco.2026.44.16_suppl.6000",
      "pmc_id": null,
      "title": "Adjuvant radiotherapy versus observation following curative surgery for early-stage oral squamous cell carcinoma (AREST; CTRI/2017/07/009114).",
      "authors": [
        "Nair, Sudhir Vasudevan",
        "Gupta, Tejpal",
        "Rane, Swapnil Ulhas",
        "Kannan, Sadhana",
        "Ghosh-Laskar, Sarbani",
        "Pantvaidya, Gouri",
        "Chaturvedi, Pankaj",
        "Pramesh, C. S.",
        "Patil, Asawari",
        "Toprani, Rajendra",
        "Patel, Kaustubh",
        "Jani, Kinjal",
        "Mishra, Aseem",
        "Nanda, Sambit Swarup",
        "Das, Ashok Kumar",
        "Bhattacharyya, Mouchumee",
        "Thankappan, Krishnakumar",
        "Iyer, Subramania",
        "Muttath, Geetha",
        "Chhatbar, Samarth Kamlesh",
        "AREST Study - Head and Neck Cooperative Oncology Group"
      ],
      "journal": "Journal of Clinical Oncology",
      "pub_date": "2026-06-01",
      "abstract": "6000 Background: The role of adjuvant radiotherapy (RT) in early-stage, node-negative oral squamous cell carcinoma (OSCC) with one or more intermediate risk factors - such as depth of invasion (DOI) ≥5 to ≤10mm, perineural invasion (PNI), lymphovascular emboli (LVE), or poor differentiation - remains debatable and is largely based on retrospective data. This multicenter, open-label, phase III randomized controlled trial was designed to assess the impact of post-operative adjuvant RT in this setting. Methods: Patients with early-stage (pT1-T2), node-negative (pN0) OSCC undergoing adequate surgery (defined as clear margins ≥5mm and at least ipsilateral level I-III neck dissection with ≥16 nodes) with presence of one or more intermediate risk factors were screened. Eligible patients underwent stratified randomization (oral cavity subsite, PNI/LVE, and differentiation) in 1:1 ratio to either observation or adjuvant RT (60Gy in 30 fractions over 6-weeks) to the resected tumor-bed and at-risk neck nodal region after written informed consent. Primary endpoint was loco-regional recurrence-free survival (LRFS) measured from randomization to first documented event of local and/or regional recurrence from index cancer. All time-to-event outcomes were computed using Kaplan-Meier (KM) method with log-rank test for comparison and expressed as 3-year point estimates with 95% confidence intervals (CI). The planned sample size (N=392) provided 80% power at an α of 0.05 to detect a Hazard Ratio (HR) of 0.6256, assuming 3-year LRFS of 70% in the observation arm. Results: Following curative surgery, a total of 392 patients were randomized (191 to adjuvant RT; 201 to observation). Baseline characteristics were balanced between the two arms. At a median follow-up of 47.2 months (inter-quartile range=30-59.4 months), 3-year KM estimate of LRFS was 89.2% in adjuvant RT arm vs 80.9% in observation arm (HR=0.52, 95%CI=0.30-0.91; p=0.02) in the intention-to-treat (ITT) population and 91.1% vs 80.9% (HR=0.43, 95%CI=0.23-0.80; p=0.01) on per-protocol (PP) analyses. Cumulative incidence of loco-regional failure with death as competing event was 10.6% (95%CI=6.1%-15.1%) with adjuvant RT and 18.9% (95%CI=13.3%-24.6%) with observation (HR=0.52, 95%CI=0.30-0.91; p=0.021) in the ITT population and 8.7% (95%CI=4.3%-13.1%) vs 18.9% (95%CI=13.3%-24.6%) (HR=0.43, 95%CI=0.23-0.79; p=0.007) on PP analyses. Disease-free and overall survival were not significantly different between the two arms. Subgroup analysis identified oral tongue deriving higher benefit of adjuvant RT compared to buccal mucosa. Conclusions: Adjuvant RT significantly reduces risk of loco-regional recurrence for early-stage, node-negative adequately resected OSCC, particularly oral tongue. However, such reduction in loco-regional failure does not translate into significant survival benefit. Clinical trial information: CTRI/2017/07/009114.",
      "pdf_path": null,
      "source_url": "https://ascopubs.org/doi/10.1200/JCO.2026.44.16_suppl.6000",
      "note": "https://ascopubs.org/doi/10.1200/JCO.2026.44.16_suppl.6000",
      "resolved_from_review": false
    }
  ]
}
