{
  "date": "2026-05-20",
  "conference": null,
  "generated_at": 1779288891909,
  "digest": {
    "top_line": "PBS proton vs IMRT post-mastectomy reconstruction: capsular contracture comparison reported, no effect size in source.",
    "tldr": "Single breast study today: PBS proton vs IMRT capsular contracture risk in post-mastectomy reconstruction pts. No extractable effect sizes from available source. Thin meeting day for oncbrain signal.",
    "sites": [
      {
        "disease_site": "breast",
        "intro": "Capsular contracture remains a key toxicity driver in post-mastectomy RT with implants; proton-vs-photon comparison is an active question.",
        "studies": [
          {
            "name": "PBS Proton vs IMRT Capsular Contracture (Post-Mastectomy Reconstruction)",
            "tldr": "PBS proton vs IMRT capsular contracture risk in post-mastectomy reconstruction: no effect size reported in source.",
            "details": [
              "🔍 Retrospective or prospective comparison of PBS proton therapy vs IMRT in post-mastectomy pts with implant-based reconstruction; primary question: differential capsular contracture risk",
              "📊 No effect size, rates, HR, or p-value reported in source; abstract/full text not available in tweet metadata",
              "💊 PBS (pencil beam scanning) proton vs IMRT (photon); post-mastectomy setting with reconstruction (implant-based assumed)",
              "⚠️ Study design, N, follow-up duration, and primary endpoint definition not available from source tweet; IJROBP publication listed but no results extractable",
              "🔗 Capsular contracture is a known toxicity driver in post-mastectomy RT with implants; prior photon data suggest 20-40% rates at 2yr depending on fractionation and timing of reconstruction"
            ],
            "key_figure_url": null,
            "key_figure_caption": null,
            "nct": null,
            "tweet_ids": [
              1000000006
            ],
            "slug": "proton-vs-imrt-capsular-contracture-postmastectomy",
            "verdict": {
              "soc_implication": "unclear",
              "rationale": "No results extractable from source; design (prospective vs retrospective), N, and primary endpoint unknown. Cannot classify.",
              "audience": "Post-mastectomy pts with implant-based reconstruction receiving adjuvant RT"
            },
            "open_questions": [
              "Does PBS proton reduce capsular contracture vs IMRT in implant reconstruction?",
              "Is dosimetric advantage of proton clinically meaningful for implant outcomes?"
            ],
            "source_ids": [
              {
                "type": "paper",
                "id": 6
              }
            ]
          }
        ],
        "open_questions": null
      }
    ],
    "meta": {
      "clusters_total": 1,
      "studies_analyzed": 1,
      "dropped": [],
      "ocr_available": true
    }
  },
  "bookmarks": [],
  "papers": [
    {
      "id": 6,
      "pmid": null,
      "doi": "10.1016/j.ijrobp.2025.07.1298",
      "pmc_id": null,
      "title": "Does Pencil Beam Scanning Proton Therapy Impart a Higher Risk of Capsular Contracture when Compared with Intensity Modulated Photon Radiotherapy in the Post-Mastectomy Reconstruction Setting?",
      "authors": [
        "Zerey, M.M.",
        "Gal, O.",
        "Feenstra, N.",
        "Hodgson, L.",
        "Fagundes, M.A.",
        "Rodrigues, M.A.M.",
        "Botero, A.C.",
        "Gutierrez, A.",
        "Wroe, A.",
        "Fellows, Z.",
        "Medina, M.A.",
        "Panoff, J.E."
      ],
      "journal": "International Journal of Radiation Oncology*Biology*Physics",
      "pub_date": "2025-09",
      "abstract": null,
      "pdf_path": null,
      "note": "https://doi.org/10.1016/j.ijrobp.2025.07.1298"
    }
  ]
}
